gh_action_open_id_in_aws/__init__.py
gh_action_open_id_in_aws/_version.py
gh_action_open_id_in_aws/api.py
gh_action_open_id_in_aws/cf.py
gh_action_open_id_in_aws/cft-2025-04-04.json
gh_action_open_id_in_aws/docs/__init__.py
gh_action_open_id_in_aws/impl.py
gh_action_open_id_in_aws/paths.py
gh_action_open_id_in_aws/tests/__init__.py
gh_action_open_id_in_aws/tests/helper.py
gh_action_open_id_in_aws/vendor/__init__.py
gh_action_open_id_in_aws/vendor/pytest_cov_helper.py
gh_action_open_id_in_aws-1.0.1.dist-info/AUTHORS.rst
gh_action_open_id_in_aws-1.0.1.dist-info/LICENSE.txt
gh_action_open_id_in_aws-1.0.1.dist-info/METADATA
gh_action_open_id_in_aws-1.0.1.dist-info/WHEEL
gh_action_open_id_in_aws-1.0.1.dist-info/RECORD
